PrimeiroLIB/__init__.py
PrimeiroLIB/operations.py
test_lib/__init__.py
test_lib/test_lib_main.py
primeiralib-0.1.2.dist-info/METADATA
primeiralib-0.1.2.dist-info/WHEEL
primeiralib-0.1.2.dist-info/top_level.txt
primeiralib-0.1.2.dist-info/RECORD
